README.md
setup.py
villas-controller.service
bin/villas-ctl
etc/config.json
villas/controller/__init__.py
villas/controller/command.py
villas/controller/config.py
villas/controller/controller.py
villas/controller/exceptions.py
villas/controller/model.py
villas/controller/simulator.py
villas/controller/commands/__init__.py
villas/controller/commands/daemon.py
villas/controller/commands/monitor.py
villas/controller/commands/simulator.py
villas/controller/models/__init__.py
villas/controller/models/cim.py
villas/controller/models/rscad.py
villas/controller/models/rtlab.py
villas/controller/simulators/__init__.py
villas/controller/simulators/dpsim.py
villas/controller/simulators/dummy.py
villas/controller/simulators/generic.py
villas/controller/simulators/rscad.py
villas/controller/simulators/rtlab.py
villas_controller.egg-info/PKG-INFO
villas_controller.egg-info/SOURCES.txt
villas_controller.egg-info/dependency_links.txt
villas_controller.egg-info/requires.txt
villas_controller.egg-info/top_level.txt