Metadata-Version: 1.1
Name: villas-controller
Version: 0.3.0
Summary: A controller/orchestration API for real-time power system simulators
Home-page: https://www.fein-aachen.org/projects/villas-controller/
Author: Steffen Vogel
Author-email: acs-software@eonerc.rwth-aachen.de
License: GPL-3.0
Keywords: simulation controller villas
Platform: UNKNOWN
Classifier: Development Status :: 3 - Alpha
Classifier: License :: OSI Approved :: GNU General Public License v3 or later (GPLv3+)
Classifier: Programming Language :: Python :: 3
